btrdb/__init__.py
btrdb/conn.py
btrdb/endpoint.py
btrdb/exceptions.py
btrdb/point.py
btrdb/stream.py
btrdb/transformers.py
btrdb/version.py
btrdb/grpcinterface/README.md
btrdb/grpcinterface/__init__.py
btrdb/grpcinterface/btrdb.proto
btrdb/grpcinterface/btrdb_pb2.py
btrdb/grpcinterface/btrdb_pb2.pyi
btrdb/grpcinterface/btrdb_pb2_grpc.py
btrdb/utils/__init__.py
btrdb/utils/buffer.py
btrdb/utils/conversion.py
btrdb/utils/credentials.py
btrdb/utils/general.py
btrdb/utils/ray.py
btrdb/utils/timez.py
btrdb-5.34.2.dist-info/licenses/LICENSE.txt
btrdb4/__init__.py
tests/btrdb/__init__.py
tests/btrdb/test_arrow_streams.py
tests/btrdb/test_base.py
tests/btrdb/test_conn.py
tests/btrdb/test_point.py
tests/btrdb/test_stream.py
tests/btrdb/test_transformers.py
tests/btrdb/utils/__init__.py
tests/btrdb/utils/test_buffer.py
tests/btrdb/utils/test_conversions.py
tests/btrdb/utils/test_credentials.py
tests/btrdb/utils/test_general.py
tests/btrdb/utils/test_timez.py
tests/btrdb_integration/__init__.py
tests/btrdb_integration/conftest.py
tests/btrdb_integration/test_conn.py
tests/btrdb_integration/test_regressions.py
tests/btrdb_integration/test_stream.py
tests/btrdb_integration/test_streamset.py
btrdb-5.34.2.dist-info/METADATA
btrdb-5.34.2.dist-info/WHEEL
btrdb-5.34.2.dist-info/top_level.txt
btrdb-5.34.2.dist-info/RECORD
