Metadata-Version: 2.4
Name: btrdb
Version: 5.34.2
Summary: Bindings to interact with the Berkeley Tree Database using gRPC.
Download-URL: https://github.com/PingThingsIO/btrdb-python/tarball/v5.34.2
Author: PingThingsIO
Author-email: PingThingsIO <support@pingthings.io>
Maintainer: PingThingsIO
Maintainer-email: PingThingsIO <support@pingthings.io>
License: Copyright (c) 2017 Sam Kumar <samkumar@berkeley.edu>
Project-URL: Docs, https://btrdb-python.readthedocs.io/
Project-URL: Repository, https://github.com/pingthingsio/btrdb-python.git
Keywords: btrdb,berkeley,timeseries,database,bindings,gRPC
Classifier: Development Status :: 5 - Production/Stable
Classifier: Intended Audience :: Developers
Classifier: Intended Audience :: Information Technology
Classifier: Intended Audience :: Science/Research
Classifier: License :: OSI Approved :: BSD License
Classifier: Natural Language :: English
Classifier: Operating System :: OS Independent
Classifier: Programming Language :: Python
Classifier: Programming Language :: Python :: 3.7
Classifier: Programming Language :: Python :: 3.8
Classifier: Programming Language :: Python :: 3.9
Classifier: Programming Language :: Python :: 3.10
Classifier: Programming Language :: Python :: 3.11
Classifier: Programming Language :: Python :: 3.12
Classifier: Topic :: Database
Classifier: Topic :: Software Development :: Libraries :: Python Modules
Requires-Python: >=3.6, <4
License-File: LICENSE.txt
Requires-Dist: grpcio
Requires-Dist: grpcio-tools
Requires-Dist: pytz
Requires-Dist: pyyaml
Requires-Dist: certifi
Provides-Extra: data
Requires-Dist: pyarrow; extra == "data"
Requires-Dist: pandas>=2.0; extra == "data"
Requires-Dist: polars; extra == "data"
Requires-Dist: numpy; extra == "data"
Requires-Dist: tabulate; extra == "data"
Provides-Extra: ray
Requires-Dist: btrdb[data]; extra == "ray"
Requires-Dist: ray; extra == "ray"
Provides-Extra: testing
Requires-Dist: btrdb[data]; extra == "testing"
Requires-Dist: pytest; extra == "testing"
Requires-Dist: freezegun; extra == "testing"
Requires-Dist: pytest-cov; extra == "testing"
Requires-Dist: pytest-flake8; extra == "testing"
Provides-Extra: all
Requires-Dist: btrdb[data]; extra == "all"
Requires-Dist: btrdb[ray]; extra == "all"
Requires-Dist: btrdb[testing]; extra == "all"
Dynamic: author
Dynamic: download-url
Dynamic: license-file
Dynamic: maintainer
Dynamic: requires-python
